simple_pyspin/__init__.py
simple_pyspin-0.1.1.dist-info/LICENSE
simple_pyspin-0.1.1.dist-info/METADATA
simple_pyspin-0.1.1.dist-info/WHEEL
simple_pyspin-0.1.1.dist-info/top_level.txt
simple_pyspin-0.1.1.dist-info/RECORD
