Metadata-Version: 2.1
Name: simple-pyspin
Version: 0.1.1
Summary: An easy-to-use Pythonic wrapper for the FLIR PySpin Library.  Developed by the Kleckner Lab at UC Merced.
Home-page: https://github.com/klecknerlab/simple_pyspin
Author: Dustin Kleckner
Author-email: dkleckner@ucmerced.edu
License: Apache 2.0 (http://www.apache.org/licenses/LICENSE-2.0)
Platform: UNKNOWN
Classifier: Programming Language :: Python :: 3
Classifier: Development Status :: 4 - Beta
Classifier: License :: OSI Approved :: Apache Software License
Classifier: Operating System :: OS Independent
